model/__init__.py
model/motif_counting.py
model/motif_list.py
motifcal-0.0.2.dist-info/LICENSE.txt
motifcal-0.0.2.dist-info/METADATA
motifcal-0.0.2.dist-info/WHEEL
motifcal-0.0.2.dist-info/top_level.txt
motifcal-0.0.2.dist-info/RECORD
